README.md
setup.py
leoproj/__init__.py
leoproj.egg-info/PKG-INFO
leoproj.egg-info/SOURCES.txt
leoproj.egg-info/dependency_links.txt
leoproj.egg-info/top_level.txt